HadeelAI/__init__.py
HadeelAI/search_problem.py
hadeelai-0.1.0.dist-info/licenses/LICENSE
hadeelai-0.1.0.dist-info/METADATA
hadeelai-0.1.0.dist-info/WHEEL
hadeelai-0.1.0.dist-info/top_level.txt
hadeelai-0.1.0.dist-info/RECORD
