Metadata-Version: 2.4
Name: HadeelAI
Version: 0.1.0
Summary: A simple search problem package
Author: Hadel Dhiany
Author-email: Hadeel Dhiany <hadeldhaiany2005@gmail.com>
License: MIT
Requires-Python: >=3.8
License-File: LICENSE
Dynamic: author
Dynamic: license-file
Dynamic: requires-python
